ingrain/__init__.py
ingrain/client.py
ingrain/ingrain_errors.py
ingrain/model.py
ingrain/pycurl_engine.py
ingrain/utils.py
ingrain/models/__init__.py
ingrain/models/camel_model.py
ingrain/models/request_models.py
ingrain/models/response_models.py
ingrain-0.2.3.dist-info/METADATA
ingrain-0.2.3.dist-info/WHEEL
ingrain-0.2.3.dist-info/top_level.txt
ingrain-0.2.3.dist-info/RECORD
