Metadata-Version: 2.4
Name: ingrain
Version: 0.2.3
Summary: Python client for the ingrain server
Requires-Python: >=3.11
Requires-Dist: certifi>=2025
Requires-Dist: numpy>=2
Requires-Dist: pycurl>=7
Requires-Dist: pydantic>=2
